tools/__init__.py
tools/cert_key_parser.py
tools/cert_utils.py
tools/config.py
tools/gen_p10.py
tools/http_utils.py
tools/json_utils.py
yop_mcp/__init__.py
yop_mcp/main.py
yop_mcp-0.1.3.dist-info/METADATA
yop_mcp-0.1.3.dist-info/WHEEL
yop_mcp-0.1.3.dist-info/entry_points.txt
yop_mcp-0.1.3.dist-info/licenses/LICENSE
yop_mcp-0.1.3.dist-info/RECORD
