Metadata-Version: 2.4
Name: yop-mcp
Version: 0.1.3
Summary: 快速对接易宝支付开放平台(YOP)的 MCP Server
Project-URL: Homepage, https://open.yeepay.com
Project-URL: Documentation, https://open.yeepay.com/docs
Project-URL: Repository, http://gitlab.yeepay.com/yop/yop-mcp.git
Project-URL: Issues, http://gitlab.yeepay.com/yop/yop-mcp/-/issues
Project-URL: Changelog, http://gitlab.yeepay.com/yop/yop-mcp/-/blob/main/CHANGELOG.md
Author-email: YOP Team <yop@yeepay.com>
Maintainer-email: YOP Team <yop@yeepay.com>
License: Apache-2.0
License-File: LICENSE
Keywords: api,mcp,payment,yeepay,yop
Classifier: Development Status :: 4 - Beta
Classifier: Intended Audience :: Developers
Classifier: License :: OSI Approved :: Apache Software License
Classifier: Operating System :: OS Independent
Classifier: Programming Language :: Python :: 3
Classifier: Programming Language :: Python :: 3.10
Classifier: Programming Language :: Python :: 3.11
Classifier: Programming Language :: Python :: 3.12
Classifier: Topic :: Internet :: WWW/HTTP :: HTTP Servers
Classifier: Topic :: Office/Business :: Financial :: Point-Of-Sale
Classifier: Topic :: Software Development :: Libraries :: Python Modules
Requires-Python: >=3.10
Requires-Dist: cryptography>=42.0.0
Requires-Dist: gmssl>=3.2.2
Requires-Dist: httpx[http2]>=0.28.1
Requires-Dist: mcp[cli]>=1.6.0
Provides-Extra: dev
Requires-Dist: bandit>=1.7.5; extra == 'dev'
Requires-Dist: black>=24.0.0; extra == 'dev'
Requires-Dist: flake8>=7.0.0; extra == 'dev'
Requires-Dist: isort>=5.13.0; extra == 'dev'
Requires-Dist: mypy>=1.8.0; extra == 'dev'
Requires-Dist: pre-commit>=3.6.0; extra == 'dev'
Requires-Dist: pylint>=3.3.0; extra == 'dev'
Requires-Dist: pytest-asyncio>=0.23.0; extra == 'dev'
Requires-Dist: pytest-cov>=4.0.0; extra == 'dev'
Requires-Dist: pytest>=8.0.0; extra == 'dev'
Requires-Dist: safety>=3.0.0; extra == 'dev'
Provides-Extra: test
Requires-Dist: httpx>=0.28.1; extra == 'test'
Requires-Dist: pytest-asyncio>=0.23.0; extra == 'test'
Requires-Dist: pytest-cov>=4.0.0; extra == 'test'
Requires-Dist: pytest>=8.0.0; extra == 'test'
